dynn/__init__.py
dynn/activations.py
dynn/operations.py
dynn/parameter_initialization.py
dynn/util.py
dynn/data/__init__.py
dynn/data/batching.py
dynn/data/batching.py.326482200cc300e4a279cd1672413b12.py
dynn/data/data_util.py
dynn/data/data_util.py.effae71710f55cb92d0b76f11e7c73fd.py
dynn/data/mnist.py
dynn/layers/__init__.py
dynn/layers/base_layer.py
dynn/layers/base_layers.py
dynn/layers/combination_layers.py
dynn/layers/convolution_layers.py
dynn/layers/convolution_layers.py.1148f7b5b69ab1d9e5905a145b149d58.py
dynn/layers/dense_layers.py
dynn/layers/lstm.py
dynn/layers/normalization_layers.py
dynn/layers/pooling_layers.py
dynn/layers/recurrent_layers.py
dynn/layers/rnn.py
dynn/layers/sequence_transduction_layers.py
dynn/layers/transduction_layers.py
dynn-0.0.12.dist-info/DESCRIPTION.rst
dynn-0.0.12.dist-info/METADATA
dynn-0.0.12.dist-info/RECORD
dynn-0.0.12.dist-info/WHEEL
dynn-0.0.12.dist-info/metadata.json
dynn-0.0.12.dist-info/top_level.txt
tests/__init__.py
tests/layers/__init__.py
tests/layers/test_dense_layers.py
tests/layers/test_lstm.py
