Metadata-Version: 2.0
Name: dynn
Version: 0.0.12
Summary: Neural networks routines for DyNet
Home-page: https://github.com/pmichel31415/dynn
Author: Paul Michel
Author-email: pmichel1@cs.cmu.edu
License: MIT License
Platform: UNKNOWN
Classifier: License :: OSI Approved :: MIT License
Classifier: Programming Language :: Python
Requires-Python: >=3.6
Requires-Dist: dynet
